<chargeDetailHolder>
    <charges>
        <Description>Property Liability Program (05/2021)</Description>
        <TransactionDate>2021-05-01</TransactionDate>
        <ChargeCode>RTRINSINC</ChargeCode>
        <CustomerID>d9dcf7f6-24c6-4a21-b150-30e4ca02afe7</CustomerID>
        <UnitID>1312</UnitID>
        <Amount>15.00</Amount>
        <BatchID>0</BatchID>
        <PropertyPrimaryID>473bf90a-24bb-495a-8044-8f8c01059601</PropertyPrimaryID>
    </charges>
    <charges>
        <Description>Property Liability Program (05/2021)</Description>
        <TransactionDate>2021-05-01</TransactionDate>
        <ChargeCode>RTRINSINC</ChargeCode>
        <CustomerID>01945600-7943-47c1-9a4e-73a2331e9ff6</CustomerID>
        <UnitID>2324</UnitID>
        <Amount>15.00</Amount>
        <BatchID>0</BatchID>
        <PropertyPrimaryID>473bf90a-24bb-495a-8044-8f8c01059601</PropertyPrimaryID>
    </charges>
    <charges>
        <Description>Property Liability Program (05/2021)</Description>
        <TransactionDate>2021-05-01</TransactionDate>
        <ChargeCode>RTRINSINC</ChargeCode>
        <CustomerID>8365daa5-2dfa-4d18-a281-dff652081f53</CustomerID>
        <UnitID>1431</UnitID>
        <Amount>15.00</Amount>
        <BatchID>0</BatchID>
        <PropertyPrimaryID>473bf90a-24bb-495a-8044-8f8c01059601</PropertyPrimaryID>
    </charges>
    <charges>
        <Description>Property Liability Program (05/2021)</Description>
        <TransactionDate>2021-05-01</TransactionDate>
        <ChargeCode>RTRINSINC</ChargeCode>
        <CustomerID>427d2574-2345-4e0d-9873-e475c512abac</CustomerID>
        <UnitID>2454</UnitID>
        <Amount>15.00</Amount>
        <BatchID>0</BatchID>
        <PropertyPrimaryID>473bf90a-24bb-495a-8044-8f8c01059601</PropertyPrimaryID>
    </charges>
    <charges>
        <Description>Property Liability Program (05/2021)</Description>
        <TransactionDate>2021-05-01</TransactionDate>
        <ChargeCode>RTRINSINC</ChargeCode>
        <CustomerID>44885e45-a9c3-4c04-a6f2-96b62682ed62</CustomerID>
        <UnitID>1304</UnitID>
        <Amount>15.00</Amount>
        <BatchID>0</BatchID>
        <PropertyPrimaryID>473bf90a-24bb-495a-8044-8f8c01059601</PropertyPrimaryID>
    </charges>
    <charges>
        <Description>Property Liability Program (05/2021)</Description>
        <TransactionDate>2021-05-01</TransactionDate>
        <ChargeCode>RTRINSINC</ChargeCode>
        <CustomerID>a2fbf4fc-bb0a-425f-9038-d5b319da9833</CustomerID>
        <UnitID>2449</UnitID>
        <Amount>15.00</Amount>
        <BatchID>0</BatchID>
        <PropertyPrimaryID>473bf90a-24bb-495a-8044-8f8c01059601</PropertyPrimaryID>
    </charges>
    <charges>
        <Description>Property Liability Program (05/2021)</Description>
        <TransactionDate>2021-05-01</TransactionDate>
        <ChargeCode>RTRINSINC</ChargeCode>
        <CustomerID>38974caa-bfbe-4c8f-82cc-dda70878218d</CustomerID>
        <UnitID>2311</UnitID>
        <Amount>15.00</Amount>
        <BatchID>0</BatchID>
        <PropertyPrimaryID>473bf90a-24bb-495a-8044-8f8c01059601</PropertyPrimaryID>
    </charges>
    <charges>
        <Description>Property Liability Program (05/2021)</Description>
        <TransactionDate>2021-05-01</TransactionDate>
        <ChargeCode>RTRINSINC</ChargeCode>
        <CustomerID>405d27d2-3a0c-45e3-816b-1d2867f0f54e</CustomerID>
        <UnitID>2339</UnitID>
        <Amount>15.00</Amount>
        <BatchID>0</BatchID>
        <PropertyPrimaryID>473bf90a-24bb-495a-8044-8f8c01059601</PropertyPrimaryID>
    </charges>
    <charges>
        <Description>Property Liability Program (05/2021)</Description>
        <TransactionDate>2021-05-01</TransactionDate>
        <ChargeCode>RTRINSINC</ChargeCode>
        <CustomerID>5a5bda77-b14c-4842-a026-2310d9d58435</CustomerID>
        <UnitID>2332</UnitID>
        <Amount>15.00</Amount>
        <BatchID>0</BatchID>
        <PropertyPrimaryID>473bf90a-24bb-495a-8044-8f8c01059601</PropertyPrimaryID>
    </charges>
    <charges>
        <Description>Property Liability Program (05/2021)</Description>
        <TransactionDate>2021-05-01</TransactionDate>
        <ChargeCode>RTRINSINC</ChargeCode>
        <CustomerID>c44b1ce9-f01e-42ef-b3ad-b0330480a5b8</CustomerID>
        <UnitID>2102</UnitID>
        <Amount>15.00</Amount>
        <BatchID>0</BatchID>
        <PropertyPrimaryID>473bf90a-24bb-495a-8044-8f8c01059601</PropertyPrimaryID>
    </charges>
    <charges>
        <Description>Property Liability Program (05/2021)</Description>
        <TransactionDate>2021-05-01</TransactionDate>
        <ChargeCode>RTRINSINC</ChargeCode>
        <CustomerID>239caec7-3046-4828-81e7-4a676dcfa991</CustomerID>
        <UnitID>1124</UnitID>
        <Amount>15.00</Amount>
        <BatchID>0</BatchID>
        <PropertyPrimaryID>473bf90a-24bb-495a-8044-8f8c01059601</PropertyPrimaryID>
    </charges>
    <charges>
        <Description>Property Liability Program (05/2021)</Description>
        <TransactionDate>2021-05-01</TransactionDate>
        <ChargeCode>RTRINSINC</ChargeCode>
        <CustomerID>881299ed-428f-471b-8954-4fe8a146d0fe</CustomerID>
        <UnitID>1444</UnitID>
        <Amount>15.00</Amount>
        <BatchID>0</BatchID>
        <PropertyPrimaryID>473bf90a-24bb-495a-8044-8f8c01059601</PropertyPrimaryID>
    </charges>
    <charges>
        <Description>Property Liability Program (05/2021)</Description>
        <TransactionDate>2021-05-01</TransactionDate>
        <ChargeCode>RTRINSINC</ChargeCode>
        <CustomerID>4cac4550-997d-43c0-932a-b5bc7c95f017</CustomerID>
        <UnitID>1105</UnitID>
        <Amount>15.00</Amount>
        <BatchID>0</BatchID>
        <PropertyPrimaryID>473bf90a-24bb-495a-8044-8f8c01059601</PropertyPrimaryID>
    </charges>
    <charges>
        <Description>Property Liability Program (05/2021)</Description>
        <TransactionDate>2021-05-01</TransactionDate>
        <ChargeCode>RTRINSINC</ChargeCode>
        <CustomerID>c9123c75-6272-46ac-9558-5766f08dd7ba</CustomerID>
        <UnitID>1434</UnitID>
        <Amount>15.00</Amount>
        <BatchID>0</BatchID>
        <PropertyPrimaryID>473bf90a-24bb-495a-8044-8f8c01059601</PropertyPrimaryID>
    </charges>
    <charges>
        <Description>Property Liability Program (05/2021)</Description>
        <TransactionDate>2021-05-01</TransactionDate>
        <ChargeCode>RTRINSINC</ChargeCode>
        <CustomerID>13d1396c-2f4a-47aa-8643-e476a73ff456</CustomerID>
        <UnitID>1441</UnitID>
        <Amount>15.00</Amount>
        <BatchID>0</BatchID>
        <PropertyPrimaryID>473bf90a-24bb-495a-8044-8f8c01059601</PropertyPrimaryID>
    </charges>
    <charges>
        <Description>Property Liability Program (05/2021)</Description>
        <TransactionDate>2021-05-01</TransactionDate>
        <ChargeCode>RTRINSINC</ChargeCode>
        <CustomerID>31d53f36-3744-44f4-9baf-cf44b24a8bd6</CustomerID>
        <UnitID>2430</UnitID>
        <Amount>15.00</Amount>
        <BatchID>0</BatchID>
        <PropertyPrimaryID>473bf90a-24bb-495a-8044-8f8c01059601</PropertyPrimaryID>
    </charges>
    <charges>
        <Description>Property Liability Program (05/2021)</Description>
        <TransactionDate>2021-05-01</TransactionDate>
        <ChargeCode>RTRINSINC</ChargeCode>
        <CustomerID>0a77e6ed-b539-40c8-9d5d-72070543f3ae</CustomerID>
        <UnitID>2340</UnitID>
        <Amount>15.00</Amount>
        <BatchID>0</BatchID>
        <PropertyPrimaryID>473bf90a-24bb-495a-8044-8f8c01059601</PropertyPrimaryID>
    </charges>
    <charges>
        <Description>Property Liability Program (05/2021)</Description>
        <TransactionDate>2021-05-01</TransactionDate>
        <ChargeCode>RTRINSINC</ChargeCode>
        <CustomerID>1e6b6975-f07b-4d66-aa0e-58d6466c25ad</CustomerID>
        <UnitID>1332</UnitID>
        <Amount>15.00</Amount>
        <BatchID>0</BatchID>
        <PropertyPrimaryID>473bf90a-24bb-495a-8044-8f8c01059601</PropertyPrimaryID>
    </charges>
    <charges>
        <Description>Property Liability Program (05/2021)</Description>
        <TransactionDate>2021-05-01</TransactionDate>
        <ChargeCode>RTRINSINC</ChargeCode>
        <CustomerID>8845d43e-2b85-4bda-be76-c1d7057c356b</CustomerID>
        <UnitID>2116</UnitID>
        <Amount>15.00</Amount>
        <BatchID>0</BatchID>
        <PropertyPrimaryID>473bf90a-24bb-495a-8044-8f8c01059601</PropertyPrimaryID>
    </charges>
    <charges>
        <Description>Property Liability Program (05/2021)</Description>
        <TransactionDate>2021-05-01</TransactionDate>
        <ChargeCode>RTRINSINC</ChargeCode>
        <CustomerID>36f73004-0bee-4889-9493-6431fb227334</CustomerID>
        <UnitID>2304</UnitID>
        <Amount>15.00</Amount>
        <BatchID>0</BatchID>
        <PropertyPrimaryID>473bf90a-24bb-495a-8044-8f8c01059601</PropertyPrimaryID>
    </charges>
    <charges>
        <Description>Property Liability Program (05/2021)</Description>
        <TransactionDate>2021-05-01</TransactionDate>
        <ChargeCode>RTRINSINC</ChargeCode>
        <CustomerID>d60a4538-e850-4f0c-9297-d6a3858fd41d</CustomerID>
        <UnitID>2346</UnitID>
        <Amount>15.00</Amount>
        <BatchID>0</BatchID>
        <PropertyPrimaryID>473bf90a-24bb-495a-8044-8f8c01059601</PropertyPrimaryID>
    </charges>
    <charges>
        <Description>Property Liability Program (05/2021)</Description>
        <TransactionDate>2021-05-01</TransactionDate>
        <ChargeCode>RTRINSINC</ChargeCode>
        <CustomerID>6a0311f9-67a1-4617-8283-16f706e3a194</CustomerID>
        <UnitID>1202</UnitID>
        <Amount>15.00</Amount>
        <BatchID>0</BatchID>
        <PropertyPrimaryID>473bf90a-24bb-495a-8044-8f8c01059601</PropertyPrimaryID>
    </charges>
    <charges>
        <Description>Property Liability Program (05/2021)</Description>
        <TransactionDate>2021-05-01</TransactionDate>
        <ChargeCode>RTRINSINC</ChargeCode>
        <CustomerID>8762a63a-f233-47e0-8194-c41ba1b37545</CustomerID>
        <UnitID>2452</UnitID>
        <Amount>15.00</Amount>
        <BatchID>0</BatchID>
        <PropertyPrimaryID>473bf90a-24bb-495a-8044-8f8c01059601</PropertyPrimaryID>
    </charges>
    <charges>
        <Description>Property Liability Program (05/2021)</Description>
        <TransactionDate>2021-05-01</TransactionDate>
        <ChargeCode>RTRINSINC</ChargeCode>
        <CustomerID>883a215e-f9b0-42d8-ba0c-c0e4f50deedd</CustomerID>
        <UnitID>1119</UnitID>
        <Amount>15.00</Amount>
        <BatchID>0</BatchID>
        <PropertyPrimaryID>473bf90a-24bb-495a-8044-8f8c01059601</PropertyPrimaryID>
    </charges>
    <charges>
        <Description>Property Liability Program (05/2021)</Description>
        <TransactionDate>2021-05-01</TransactionDate>
        <ChargeCode>RTRINSINC</ChargeCode>
        <CustomerID>075b89f2-ea8c-45b1-91bf-fccf3405966f</CustomerID>
        <UnitID>2123</UnitID>
        <Amount>15.00</Amount>
        <BatchID>0</BatchID>
        <PropertyPrimaryID>473bf90a-24bb-495a-8044-8f8c01059601</PropertyPrimaryID>
    </charges>
    <charges>
        <Description>Property Liability Program (05/2021)</Description>
        <TransactionDate>2021-05-01</TransactionDate>
        <ChargeCode>RTRINSINC</ChargeCode>
        <CustomerID>c3193ea5-2870-47bf-b1a6-18d73ab1693a</CustomerID>
        <UnitID>2402</UnitID>
        <Amount>15.00</Amount>
        <BatchID>0</BatchID>
        <PropertyPrimaryID>473bf90a-24bb-495a-8044-8f8c01059601</PropertyPrimaryID>
    </charges>
    <charges>
        <Description>Property Liability Program (05/2021)</Description>
        <TransactionDate>2021-05-01</TransactionDate>
        <ChargeCode>RTRINSINC</ChargeCode>
        <CustomerID>728827a1-216c-4bdd-ba3c-4eaaa1ea86f9</CustomerID>
        <UnitID>2423</UnitID>
        <Amount>15.00</Amount>
        <BatchID>0</BatchID>
        <PropertyPrimaryID>473bf90a-24bb-495a-8044-8f8c01059601</PropertyPrimaryID>
    </charges>
    <charges>
        <Description>Property Liability Program (05/2021)</Description>
        <TransactionDate>2021-05-01</TransactionDate>
        <ChargeCode>RTRINSINC</ChargeCode>
        <CustomerID>e2a59d8f-6b39-4767-abf3-ecff65ea6eb2</CustomerID>
        <UnitID>1102</UnitID>
        <Amount>15.00</Amount>
        <BatchID>0</BatchID>
        <PropertyPrimaryID>473bf90a-24bb-495a-8044-8f8c01059601</PropertyPrimaryID>
    </charges>
    <charges>
        <Description>Property Liability Program (05/2021)</Description>
        <TransactionDate>2021-05-01</TransactionDate>
        <ChargeCode>RTRINSINC</ChargeCode>
        <CustomerID>b746509a-18da-4b73-ba91-bee535934399</CustomerID>
        <UnitID>2415</UnitID>
        <Amount>15.00</Amount>
        <BatchID>0</BatchID>
        <PropertyPrimaryID>473bf90a-24bb-495a-8044-8f8c01059601</PropertyPrimaryID>
    </charges>
    <charges>
        <Description>Property Liability Program (05/2021)</Description>
        <TransactionDate>2021-05-01</TransactionDate>
        <ChargeCode>RTRINSINC</ChargeCode>
        <CustomerID>2d63fe66-8a79-4283-ad58-eedee7c7e980</CustomerID>
        <UnitID>1445</UnitID>
        <Amount>15.00</Amount>
        <BatchID>0</BatchID>
        <PropertyPrimaryID>473bf90a-24bb-495a-8044-8f8c01059601</PropertyPrimaryID>
    </charges>
    <charges>
        <Description>Property Liability Program (05/2021)</Description>
        <TransactionDate>2021-05-01</TransactionDate>
        <ChargeCode>RTRINSINC</ChargeCode>
        <CustomerID>9840d4f3-0de8-499f-8b88-3175113b19f3</CustomerID>
        <UnitID>2450</UnitID>
        <Amount>15.00</Amount>
        <BatchID>0</BatchID>
        <PropertyPrimaryID>473bf90a-24bb-495a-8044-8f8c01059601</PropertyPrimaryID>
    </charges>
    <charges>
        <Description>Property Liability Program (05/2021)</Description>
        <TransactionDate>2021-05-01</TransactionDate>
        <ChargeCode>RTRINSINC</ChargeCode>
        <CustomerID>0ab5bd92-c939-426b-a8a5-e5284d03cb07</CustomerID>
        <UnitID>2205</UnitID>
        <Amount>15.00</Amount>
        <BatchID>0</BatchID>
        <PropertyPrimaryID>473bf90a-24bb-495a-8044-8f8c01059601</PropertyPrimaryID>
    </charges>
    <charges>
        <Description>Property Liability Program (05/2021)</Description>
        <TransactionDate>2021-05-01</TransactionDate>
        <ChargeCode>RTRINSINC</ChargeCode>
        <CustomerID>6faf8ac7-52e9-4b70-a12d-2c2b575d6824</CustomerID>
        <UnitID>1115</UnitID>
        <Amount>15.00</Amount>
        <BatchID>0</BatchID>
        <PropertyPrimaryID>473bf90a-24bb-495a-8044-8f8c01059601</PropertyPrimaryID>
    </charges>
    <charges>
        <Description>Property Liability Program (05/2021)</Description>
        <TransactionDate>2021-05-01</TransactionDate>
        <ChargeCode>RTRINSINC</ChargeCode>
        <CustomerID>8ba4c19c-3457-4626-b5f7-b9f7a445bd7b</CustomerID>
        <UnitID>1104</UnitID>
        <Amount>15.00</Amount>
        <BatchID>0</BatchID>
        <PropertyPrimaryID>473bf90a-24bb-495a-8044-8f8c01059601</PropertyPrimaryID>
    </charges>
    <charges>
        <Description>Property Liability Program (05/2021)</Description>
        <TransactionDate>2021-05-01</TransactionDate>
        <ChargeCode>RTRINSINC</ChargeCode>
        <CustomerID>636ee19e-0857-4768-9fd1-f76f719c3bf2</CustomerID>
        <UnitID>1114</UnitID>
        <Amount>15.00</Amount>
        <BatchID>0</BatchID>
        <PropertyPrimaryID>473bf90a-24bb-495a-8044-8f8c01059601</PropertyPrimaryID>
    </charges>
    <charges>
        <Description>Property Liability Program (05/2021)</Description>
        <TransactionDate>2021-05-01</TransactionDate>
        <ChargeCode>RTRINSINC</ChargeCode>
        <CustomerID>008d74a7-4f1c-45e2-9940-872a105b08a3</CustomerID>
        <UnitID>1314</UnitID>
        <Amount>15.00</Amount>
        <BatchID>0</BatchID>
        <PropertyPrimaryID>473bf90a-24bb-495a-8044-8f8c01059601</PropertyPrimaryID>
    </charges>
    <charges>
        <Description>Property Liability Program (05/2021)</Description>
        <TransactionDate>2021-05-01</TransactionDate>
        <ChargeCode>RTRINSINC</ChargeCode>
        <CustomerID>a49ff3b2-13ce-4f00-b382-53ee109b555d</CustomerID>
        <UnitID>2426</UnitID>
        <Amount>15.00</Amount>
        <BatchID>0</BatchID>
        <PropertyPrimaryID>473bf90a-24bb-495a-8044-8f8c01059601</PropertyPrimaryID>
    </charges>
    <charges>
        <Description>Property Liability Program (05/2021)</Description>
        <TransactionDate>2021-05-01</TransactionDate>
        <ChargeCode>RTRINSINC</ChargeCode>
        <CustomerID>05b25ab8-a5da-409d-aaf5-1d44c42c945a</CustomerID>
        <UnitID>1208</UnitID>
        <Amount>15.00</Amount>
        <BatchID>0</BatchID>
        <PropertyPrimaryID>473bf90a-24bb-495a-8044-8f8c01059601</PropertyPrimaryID>
    </charges>
    <charges>
        <Description>Property Liability Program (05/2021)</Description>
        <TransactionDate>2021-05-01</TransactionDate>
        <ChargeCode>RTRINSINC</ChargeCode>
        <CustomerID>9fbf418b-1813-4470-9ee3-cf6177f7970f</CustomerID>
        <UnitID>2413</UnitID>
        <Amount>15.00</Amount>
        <BatchID>0</BatchID>
        <PropertyPrimaryID>473bf90a-24bb-495a-8044-8f8c01059601</PropertyPrimaryID>
    </charges>
    <charges>
        <Description>Property Liability Program (05/2021)</Description>
        <TransactionDate>2021-05-01</TransactionDate>
        <ChargeCode>RTRINSINC</ChargeCode>
        <CustomerID>eccc4700-fd07-40e3-9a7f-5fccccdcf2e3</CustomerID>
        <UnitID>2201</UnitID>
        <Amount>15.00</Amount>
        <BatchID>0</BatchID>
        <PropertyPrimaryID>473bf90a-24bb-495a-8044-8f8c01059601</PropertyPrimaryID>
    </charges>
    <charges>
        <Description>Property Liability Program (05/2021)</Description>
        <TransactionDate>2021-05-01</TransactionDate>
        <ChargeCode>RTRINSINC</ChargeCode>
        <CustomerID>86919c42-4331-4640-8d56-64512833b39f</CustomerID>
        <UnitID>2321</UnitID>
        <Amount>15.00</Amount>
        <BatchID>0</BatchID>
        <PropertyPrimaryID>473bf90a-24bb-495a-8044-8f8c01059601</PropertyPrimaryID>
    </charges>
    <charges>
        <Description>Property Liability Program (05/2021)</Description>
        <TransactionDate>2021-05-01</TransactionDate>
        <ChargeCode>RTRINSINC</ChargeCode>
        <CustomerID>f9994c99-7739-4db8-a95b-f2aca401a724</CustomerID>
        <UnitID>2301</UnitID>
        <Amount>15.00</Amount>
        <BatchID>0</BatchID>
        <PropertyPrimaryID>473bf90a-24bb-495a-8044-8f8c01059601</PropertyPrimaryID>
    </charges>
    <charges>
        <Description>Property Liability Program (05/2021)</Description>
        <TransactionDate>2021-05-01</TransactionDate>
        <ChargeCode>RTRINSINC</ChargeCode>
        <CustomerID>6849ed90-35ef-4f4f-9fb7-dce68b2515e2</CustomerID>
        <UnitID>2455</UnitID>
        <Amount>15.00</Amount>
        <BatchID>0</BatchID>
        <PropertyPrimaryID>473bf90a-24bb-495a-8044-8f8c01059601</PropertyPrimaryID>
    </charges>
    <charges>
        <Description>Property Liability Program (05/2021)</Description>
        <TransactionDate>2021-05-01</TransactionDate>
        <ChargeCode>RTRINSINC</ChargeCode>
        <CustomerID>1772ff73-b8af-4182-83a1-0a6f7ea36368</CustomerID>
        <UnitID>1424</UnitID>
        <Amount>15.00</Amount>
        <BatchID>0</BatchID>
        <PropertyPrimaryID>473bf90a-24bb-495a-8044-8f8c01059601</PropertyPrimaryID>
    </charges>
    <charges>
        <Description>Property Liability Program (05/2021)</Description>
        <TransactionDate>2021-05-01</TransactionDate>
        <ChargeCode>RTRINSINC</ChargeCode>
        <CustomerID>990e93b1-e174-4993-94ee-99e19947458b</CustomerID>
        <UnitID>2111</UnitID>
        <Amount>15.00</Amount>
        <BatchID>0</BatchID>
        <PropertyPrimaryID>473bf90a-24bb-495a-8044-8f8c01059601</PropertyPrimaryID>
    </charges>
    <charges>
        <Description>Property Liability Program (05/2021)</Description>
        <TransactionDate>2021-05-01</TransactionDate>
        <ChargeCode>RTRINSINC</ChargeCode>
        <CustomerID>d50889bf-7ae8-4576-b930-960d4ffefb26</CustomerID>
        <UnitID>1443</UnitID>
        <Amount>15.00</Amount>
        <BatchID>0</BatchID>
        <PropertyPrimaryID>473bf90a-24bb-495a-8044-8f8c01059601</PropertyPrimaryID>
    </charges>
    <charges>
        <Description>Property Liability Program (05/2021)</Description>
        <TransactionDate>2021-05-01</TransactionDate>
        <ChargeCode>RTRINSINC</ChargeCode>
        <CustomerID>158982e8-c472-4c5e-9be8-1e05fad6fb9a</CustomerID>
        <UnitID>2202</UnitID>
        <Amount>15.00</Amount>
        <BatchID>0</BatchID>
        <PropertyPrimaryID>473bf90a-24bb-495a-8044-8f8c01059601</PropertyPrimaryID>
    </charges>
    <charges>
        <Description>Property Liability Program (05/2021)</Description>
        <TransactionDate>2021-05-01</TransactionDate>
        <ChargeCode>RTRINSINC</ChargeCode>
        <CustomerID>c2390ffe-6e89-45e8-9137-8bbb8c245758</CustomerID>
        <UnitID>2306</UnitID>
        <Amount>15.00</Amount>
        <BatchID>0</BatchID>
        <PropertyPrimaryID>473bf90a-24bb-495a-8044-8f8c01059601</PropertyPrimaryID>
    </charges>
    <charges>
        <Description>Property Liability Program (05/2021)</Description>
        <TransactionDate>2021-05-01</TransactionDate>
        <ChargeCode>RTRINSINC</ChargeCode>
        <CustomerID>086c8b2a-e784-46ff-ba41-5f30b07850e2</CustomerID>
        <UnitID>2104</UnitID>
        <Amount>15.00</Amount>
        <BatchID>0</BatchID>
        <PropertyPrimaryID>473bf90a-24bb-495a-8044-8f8c01059601</PropertyPrimaryID>
    </charges>
    <charges>
        <Description>Property Liability Program (05/2021)</Description>
        <TransactionDate>2021-05-01</TransactionDate>
        <ChargeCode>RTRINSINC</ChargeCode>
        <CustomerID>8429f45b-43a0-40d4-8025-1711eadce159</CustomerID>
        <UnitID>2345</UnitID>
        <Amount>15.00</Amount>
        <BatchID>0</BatchID>
        <PropertyPrimaryID>473bf90a-24bb-495a-8044-8f8c01059601</PropertyPrimaryID>
    </charges>
    <charges>
        <Description>Property Liability Program (05/2021)</Description>
        <TransactionDate>2021-05-01</TransactionDate>
        <ChargeCode>RTRINSINC</ChargeCode>
        <CustomerID>c8160240-c2fe-4ea0-a2f5-ccb98f4ac54c</CustomerID>
        <UnitID>1439</UnitID>
        <Amount>15.00</Amount>
        <BatchID>0</BatchID>
        <PropertyPrimaryID>473bf90a-24bb-495a-8044-8f8c01059601</PropertyPrimaryID>
    </charges>
    <charges>
        <Description>Property Liability Program (05/2021)</Description>
        <TransactionDate>2021-05-01</TransactionDate>
        <ChargeCode>RTRINSINC</ChargeCode>
        <CustomerID>844ca09f-aaed-4960-a61f-a4a00d48170f</CustomerID>
        <UnitID>1423</UnitID>
        <Amount>15.00</Amount>
        <BatchID>0</BatchID>
        <PropertyPrimaryID>473bf90a-24bb-495a-8044-8f8c01059601</PropertyPrimaryID>
    </charges>
    <charges>
        <Description>Property Liability Program (05/2021)</Description>
        <TransactionDate>2021-05-01</TransactionDate>
        <ChargeCode>RTRINSINC</ChargeCode>
        <CustomerID>cf68910c-4b95-4dc0-9507-a5a1af0ac34f</CustomerID>
        <UnitID>1333</UnitID>
        <Amount>15.00</Amount>
        <BatchID>0</BatchID>
        <PropertyPrimaryID>473bf90a-24bb-495a-8044-8f8c01059601</PropertyPrimaryID>
    </charges>
    <charges>
        <Description>Property Liability Program (05/2021)</Description>
        <TransactionDate>2021-05-01</TransactionDate>
        <ChargeCode>RTRINSINC</ChargeCode>
        <CustomerID>99be36f7-9a20-4a00-a50c-21c244316666</CustomerID>
        <UnitID>2327</UnitID>
        <Amount>15.00</Amount>
        <BatchID>0</BatchID>
        <PropertyPrimaryID>473bf90a-24bb-495a-8044-8f8c01059601</PropertyPrimaryID>
    </charges>
    <charges>
        <Description>Property Liability Program (05/2021)</Description>
        <TransactionDate>2021-05-01</TransactionDate>
        <ChargeCode>RTRINSINC</ChargeCode>
        <CustomerID>d27a6045-1531-45ae-a281-414502a8fcb6</CustomerID>
        <UnitID>1420</UnitID>
        <Amount>15.00</Amount>
        <BatchID>0</BatchID>
        <PropertyPrimaryID>473bf90a-24bb-495a-8044-8f8c01059601</PropertyPrimaryID>
    </charges>
    <charges>
        <Description>Property Liability Program (05/2021)</Description>
        <TransactionDate>2021-05-01</TransactionDate>
        <ChargeCode>RTRINSINC</ChargeCode>
        <CustomerID>dcd3b77f-56e4-4dc1-a8f7-9cf0d073a8c8</CustomerID>
        <UnitID>2119</UnitID>
        <Amount>15.00</Amount>
        <BatchID>0</BatchID>
        <PropertyPrimaryID>473bf90a-24bb-495a-8044-8f8c01059601</PropertyPrimaryID>
    </charges>
    <charges>
        <Description>Property Liability Program (05/2021)</Description>
        <TransactionDate>2021-05-01</TransactionDate>
        <ChargeCode>RTRINSINC</ChargeCode>
        <CustomerID>30cd0c52-4e38-4778-bb12-19776c3264ee</CustomerID>
        <UnitID>1307</UnitID>
        <Amount>15.00</Amount>
        <BatchID>0</BatchID>
        <PropertyPrimaryID>473bf90a-24bb-495a-8044-8f8c01059601</PropertyPrimaryID>
    </charges>
    <charges>
        <Description>Property Liability Program (05/2021)</Description>
        <TransactionDate>2021-05-01</TransactionDate>
        <ChargeCode>RTRINSINC</ChargeCode>
        <CustomerID>e1dc8bbb-53f9-45c4-907a-99a1a373071b</CustomerID>
        <UnitID>1113</UnitID>
        <Amount>15.00</Amount>
        <BatchID>0</BatchID>
        <PropertyPrimaryID>473bf90a-24bb-495a-8044-8f8c01059601</PropertyPrimaryID>
    </charges>
    <charges>
        <Description>Property Liability Program (05/2021)</Description>
        <TransactionDate>2021-05-01</TransactionDate>
        <ChargeCode>RTRINSINC</ChargeCode>
        <CustomerID>c7480908-e01b-4eb1-bcee-3bbefa3ea525</CustomerID>
        <UnitID>1430</UnitID>
        <Amount>15.00</Amount>
        <BatchID>0</BatchID>
        <PropertyPrimaryID>473bf90a-24bb-495a-8044-8f8c01059601</PropertyPrimaryID>
    </charges>
    <charges>
        <Description>Property Liability Program (05/2021)</Description>
        <TransactionDate>2021-05-01</TransactionDate>
        <ChargeCode>RTRINSINC</ChargeCode>
        <CustomerID>e4f9bb03-9ad0-4795-8282-b882e188d1b4</CustomerID>
        <UnitID>1409</UnitID>
        <Amount>15.00</Amount>
        <BatchID>0</BatchID>
        <PropertyPrimaryID>473bf90a-24bb-495a-8044-8f8c01059601</PropertyPrimaryID>
    </charges>
    <charges>
        <Description>Property Liability Program (05/2021)</Description>
        <TransactionDate>2021-05-01</TransactionDate>
        <ChargeCode>RTRINSINC</ChargeCode>
        <CustomerID>3087c846-5415-49cf-867c-eb424114a5ad</CustomerID>
        <UnitID>1111</UnitID>
        <Amount>15.00</Amount>
        <BatchID>0</BatchID>
        <PropertyPrimaryID>473bf90a-24bb-495a-8044-8f8c01059601</PropertyPrimaryID>
    </charges>
    <charges>
        <Description>Property Liability Program (05/2021)</Description>
        <TransactionDate>2021-05-01</TransactionDate>
        <ChargeCode>RTRINSINC</ChargeCode>
        <CustomerID>0ee277c5-c3d9-401b-b3dd-da43f7b4f6d9</CustomerID>
        <UnitID>2109</UnitID>
        <Amount>15.00</Amount>
        <BatchID>0</BatchID>
        <PropertyPrimaryID>473bf90a-24bb-495a-8044-8f8c01059601</PropertyPrimaryID>
    </charges>
    <charges>
        <Description>Property Liability Program (05/2021)</Description>
        <TransactionDate>2021-05-01</TransactionDate>
        <ChargeCode>RTRINSINC</ChargeCode>
        <CustomerID>af18c8da-74d8-46bf-9a01-4050582d02c9</CustomerID>
        <UnitID>2444</UnitID>
        <Amount>15.00</Amount>
        <BatchID>0</BatchID>
        <PropertyPrimaryID>473bf90a-24bb-495a-8044-8f8c01059601</PropertyPrimaryID>
    </charges>
    <charges>
        <Description>Property Liability Program (05/2021)</Description>
        <TransactionDate>2021-05-01</TransactionDate>
        <ChargeCode>RTRINSINC</ChargeCode>
        <CustomerID>f37517b7-bac8-4085-a1e1-04341e7a3e21</CustomerID>
        <UnitID>2310</UnitID>
        <Amount>15.00</Amount>
        <BatchID>0</BatchID>
        <PropertyPrimaryID>473bf90a-24bb-495a-8044-8f8c01059601</PropertyPrimaryID>
    </charges>
    <charges>
        <Description>Property Liability Program (05/2021)</Description>
        <TransactionDate>2021-05-01</TransactionDate>
        <ChargeCode>RTRINSINC</ChargeCode>
        <CustomerID>6c460e3a-5ad7-47b1-ae45-5baa69616fb9</CustomerID>
        <UnitID>2453</UnitID>
        <Amount>15.00</Amount>
        <BatchID>0</BatchID>
        <PropertyPrimaryID>473bf90a-24bb-495a-8044-8f8c01059601</PropertyPrimaryID>
    </charges>
    <charges>
        <Description>Property Liability Program (05/2021)</Description>
        <TransactionDate>2021-05-01</TransactionDate>
        <ChargeCode>RTRINSINC</ChargeCode>
        <CustomerID>0051a0d2-c651-4c4b-bd20-f88ec84c4d4b</CustomerID>
        <UnitID>1108</UnitID>
        <Amount>15.00</Amount>
        <BatchID>0</BatchID>
        <PropertyPrimaryID>473bf90a-24bb-495a-8044-8f8c01059601</PropertyPrimaryID>
    </charges>
    <charges>
        <Description>Property Liability Program (05/2021)</Description>
        <TransactionDate>2021-05-01</TransactionDate>
        <ChargeCode>RTRINSINC</ChargeCode>
        <CustomerID>2deb3a97-01d4-432c-add5-0b3714081678</CustomerID>
        <UnitID>2305</UnitID>
        <Amount>15.00</Amount>
        <BatchID>0</BatchID>
        <PropertyPrimaryID>473bf90a-24bb-495a-8044-8f8c01059601</PropertyPrimaryID>
    </charges>
    <charges>
        <Description>Property Liability Program (05/2021)</Description>
        <TransactionDate>2021-05-01</TransactionDate>
        <ChargeCode>RTRINSINC</ChargeCode>
        <CustomerID>4e521bda-942f-4714-a784-9f097bb48fef</CustomerID>
        <UnitID>2429</UnitID>
        <Amount>15.00</Amount>
        <BatchID>0</BatchID>
        <PropertyPrimaryID>473bf90a-24bb-495a-8044-8f8c01059601</PropertyPrimaryID>
    </charges>
    <charges>
        <Description>Property Liability Program (05/2021)</Description>
        <TransactionDate>2021-05-01</TransactionDate>
        <ChargeCode>RTRINSINC</ChargeCode>
        <CustomerID>b0d17c04-8e50-4014-b004-8b4d70adc0ae</CustomerID>
        <UnitID>1414</UnitID>
        <Amount>15.00</Amount>
        <BatchID>0</BatchID>
        <PropertyPrimaryID>473bf90a-24bb-495a-8044-8f8c01059601</PropertyPrimaryID>
    </charges>
    <charges>
        <Description>Property Liability Program (05/2021)</Description>
        <TransactionDate>2021-05-01</TransactionDate>
        <ChargeCode>RTRINSINC</ChargeCode>
        <CustomerID>b4eb7a1d-af84-4e36-aa8f-976c270bff23</CustomerID>
        <UnitID>2331</UnitID>
        <Amount>15.00</Amount>
        <BatchID>0</BatchID>
        <PropertyPrimaryID>473bf90a-24bb-495a-8044-8f8c01059601</PropertyPrimaryID>
    </charges>
    <charges>
        <Description>Property Liability Program (05/2021)</Description>
        <TransactionDate>2021-05-01</TransactionDate>
        <ChargeCode>RTRINSINC</ChargeCode>
        <CustomerID>01c61161-ff26-4e15-aede-afed0f21d2d3</CustomerID>
        <UnitID>1206</UnitID>
        <Amount>15.00</Amount>
        <BatchID>0</BatchID>
        <PropertyPrimaryID>473bf90a-24bb-495a-8044-8f8c01059601</PropertyPrimaryID>
    </charges>
    <charges>
        <Description>Property Liability Program (05/2021)</Description>
        <TransactionDate>2021-05-01</TransactionDate>
        <ChargeCode>RTRINSINC</ChargeCode>
        <CustomerID>d9ca8d04-8bc6-4ddf-9ee2-08b8490ebb73</CustomerID>
        <UnitID>1340</UnitID>
        <Amount>15.00</Amount>
        <BatchID>0</BatchID>
        <PropertyPrimaryID>473bf90a-24bb-495a-8044-8f8c01059601</PropertyPrimaryID>
    </charges>
    <charges>
        <Description>Property Liability Program (05/2021)</Description>
        <TransactionDate>2021-05-01</TransactionDate>
        <ChargeCode>RTRINSINC</ChargeCode>
        <CustomerID>5d525989-2363-4a5e-a176-1e767d49b49e</CustomerID>
        <UnitID>2329</UnitID>
        <Amount>15.00</Amount>
        <BatchID>0</BatchID>
        <PropertyPrimaryID>473bf90a-24bb-495a-8044-8f8c01059601</PropertyPrimaryID>
    </charges>
    <charges>
        <Description>Property Liability Program (05/2021)</Description>
        <TransactionDate>2021-05-01</TransactionDate>
        <ChargeCode>RTRINSINC</ChargeCode>
        <CustomerID>03bdb126-eadd-4d0c-8be0-924f79042f80</CustomerID>
        <UnitID>1352</UnitID>
        <Amount>15.00</Amount>
        <BatchID>0</BatchID>
        <PropertyPrimaryID>473bf90a-24bb-495a-8044-8f8c01059601</PropertyPrimaryID>
    </charges>
    <charges>
        <Description>Property Liability Program (05/2021)</Description>
        <TransactionDate>2021-05-01</TransactionDate>
        <ChargeCode>RTRINSINC</ChargeCode>
        <CustomerID>3e8a56dd-829d-4793-95cd-b95afd3b8e89</CustomerID>
        <UnitID>1309</UnitID>
        <Amount>15.00</Amount>
        <BatchID>0</BatchID>
        <PropertyPrimaryID>473bf90a-24bb-495a-8044-8f8c01059601</PropertyPrimaryID>
    </charges>
    <charges>
        <Description>Property Liability Program (05/2021)</Description>
        <TransactionDate>2021-05-01</TransactionDate>
        <ChargeCode>RTRINSINC</ChargeCode>
        <CustomerID>44b1f0b3-15a1-47ff-b4ae-c3f8efb951ac</CustomerID>
        <UnitID>2411</UnitID>
        <Amount>15.00</Amount>
        <BatchID>0</BatchID>
        <PropertyPrimaryID>473bf90a-24bb-495a-8044-8f8c01059601</PropertyPrimaryID>
    </charges>
    <charges>
        <Description>Property Liability Program (05/2021)</Description>
        <TransactionDate>2021-05-01</TransactionDate>
        <ChargeCode>RTRINSINC</ChargeCode>
        <CustomerID>76c65170-e507-4f3e-b68f-d89bc54db2b9</CustomerID>
        <UnitID>1341</UnitID>
        <Amount>15.00</Amount>
        <BatchID>0</BatchID>
        <PropertyPrimaryID>473bf90a-24bb-495a-8044-8f8c01059601</PropertyPrimaryID>
    </charges>
</chargeDetailHolder>
